pbSGD/__init__.py
pbSGD/pbSGD.py
pbsgd-1.0.dist-info/METADATA
pbsgd-1.0.dist-info/WHEEL
pbsgd-1.0.dist-info/top_level.txt
pbsgd-1.0.dist-info/RECORD
