Metadata-Version: 2.1
Name: pbsgd
Version: 1.0
Summary: pbSGD Optimization Algorithm for Deep Learning
Home-page: https://github.com/HAIRLAB/pbSGD
Author: Beitong Zhou
Author-email: zhoubt@hust.edu.cn
Requires-Python: >=3.6.0
Requires-Dist: torch (>=0.4.0)
